pitts/__init__.py
pitts-0.0.1.dist-info/LICENSE
pitts-0.0.1.dist-info/METADATA
pitts-0.0.1.dist-info/WHEEL
pitts-0.0.1.dist-info/top_level.txt
pitts-0.0.1.dist-info/RECORD
