Metadata-Version: 2.1
Name: pitts
Version: 0.0.1
Summary: Little package for big things
Home-page: https://github.com/quantmoon/whitehole
Author: QuantMoon Technologies
Author-email: contacto@quantmoon.com
License: UNKNOWN
Platform: UNKNOWN
Classifier: Programming Language :: Python :: 3
Classifier: License :: OSI Approved :: MIT License
Classifier: Operating System :: Microsoft :: Windows
Requires-Python: >=3.5
